imply_druid_mcp/__init__.py
imply_druid_mcp/client.py
imply_druid_mcp/config.py
imply_druid_mcp/server.py
imply_druid_mcp/utils.py
imply_druid_mcp/tools/__init__.py
imply_druid_mcp/tools/dashboard_tools.py
imply_druid_mcp/tools/datacube_tools.py
imply_druid_mcp/tools/query_tools.py
imply_druid_mcp/tools/table_tools.py
imply_druid_mcp-0.2.0.dist-info/licenses/LICENSE
imply_druid_mcp-0.2.0.dist-info/METADATA
imply_druid_mcp-0.2.0.dist-info/WHEEL
imply_druid_mcp-0.2.0.dist-info/entry_points.txt
imply_druid_mcp-0.2.0.dist-info/top_level.txt
imply_druid_mcp-0.2.0.dist-info/RECORD
