Metadata-Version: 2.4
Name: imply-druid-mcp
Version: 0.2.0
Summary: MCP server for Imply Cloud/Druid - query and manage data through AI assistants
Author: YB Hwang
License: MIT
Project-URL: Homepage, https://github.com/yeongbin-hwang/imply-druid-mcp
Project-URL: Repository, https://github.com/yeongbin-hwang/imply-druid-mcp
Project-URL: Issues, https://github.com/yeongbin-hwang/imply-druid-mcp/issues
Keywords: mcp,model-context-protocol,imply,druid,apache-druid,database,ai,llm,claude
Classifier: Development Status :: 4 - Beta
Classifier: Intended Audience :: Developers
Classifier: License :: OSI Approved :: MIT License
Classifier: Operating System :: OS Independent
Classifier: Programming Language :: Python :: 3
Classifier: Programming Language :: Python :: 3.10
Classifier: Programming Language :: Python :: 3.11
Classifier: Programming Language :: Python :: 3.12
Classifier: Topic :: Database
Classifier: Topic :: Scientific/Engineering :: Artificial Intelligence
Requires-Python: >=3.10
License-File: LICENSE
Requires-Dist: mcp>=1.0.0
Requires-Dist: httpx>=0.27.0
Requires-Dist: pydantic>=2.0.0
Requires-Dist: python-dotenv>=1.0.0
Provides-Extra: dev
Requires-Dist: pytest>=8.0.0; extra == "dev"
Requires-Dist: pytest-asyncio>=0.23.0; extra == "dev"
Requires-Dist: pytest-cov>=4.0.0; extra == "dev"
Requires-Dist: black>=24.0.0; extra == "dev"
Requires-Dist: ruff>=0.1.0; extra == "dev"
Requires-Dist: mypy>=1.8.0; extra == "dev"
Dynamic: license-file
